{
    "info": {
        "Name": "nginx",
        "Epoch": "1",
        "Version": "1.14.1",
        "Release": "9.module_el8.0.0+1060+3ab382d3",
        "Architecture": "x86_64",
        "Size": "570 k",
        "Source": "nginx-1.14.1-9.module_el8.0.0+1060+3ab382d3.src.rpm",
        "Repository": "appstream",
        "Summary": "A high performance web server and reverse proxy server",
        "URL": "http://nginx.org/",
        "License": "BSD",
        "Description": "Nginx is a web server and a reverse proxy server for HTTP, SMTP, POP3 and"
    },
    "list": [
        "nginx.x86_64          1:1.14.1-9.module_el8.0.0+184+e34fea82           appstream",
        "nginx.x86_64          1:1.14.1-9.module_el8.0.0+1060+3ab382d3          appstream"
    ],
    "kojiPackages": [
        "nginx-1.14.1-9.module_el8.0.0+184+e34fea82",
        "nginx-1.14.1-8.module_el8.0.0+5+258f653c",
        "nginx-1.14.1-9.module_el8.0.0+1060+3ab382d3"
    ]
}