{
    "info": {
        "Name": "perl",
        "Epoch": "4",
        "Version": "5.30.1",
        "Release": "448.module_f29+7048+87e9cc50",
        "Architecture": "x86_64",
        "Size": "22 k",
        "Source": "perl-5.30.1-448.module_f29+7048+87e9cc50.src.rpm",
        "Repository": "updates-modular",
        "Summary": "Practical Extraction and Report Language",
        "URL": "https://www.perl.org/",
        "License": "GPL+ or Artistic",
        "Description": "Perl is a high-level programming language with roots in C, sed,"
    },
    "list": [
        "perl.x86_64        4:5.30.1-448.module_f29+7048+87e9cc50         updates-modular"
    ],
    "kojiPackages": [
        "perl-5.30.1-448.module_f29+7048+87e9cc50",
        "perl-5.30.0-446.module_f29+6439+d6f25761",
        "perl-5.30.0-445.module_f29+6166+8b5ad319",
        "perl-5.30.0-444.module_f29+5996+e8f83c04",
        "perl-5.30.0-443.module_f29+5980+a37c92ac",
        "perl-5.30.0-443.module_f29+5301+06000d52",
        "perl-5.30.0-441.module_f29+5079+a690dde3",
        "perl-5.30.0-440.module_f29+4984+cd60abcf",
        "perl-5.30.0-440.module_f29+4964+67351ab5",
        "perl-5.30.0-440.module_f29+4866+a49eece4",
        "perl-5.30.0-440.module_f29+4861+f049eafd",
        "perl-5.30.0-440.module_f29+4857+b2520d86",
        "perl-5.30.0-440.module_f29+4854+a4ba1a1f",
        "perl-5.30.0-440.module_f29+4846+4432cf3c",
        "perl-5.30.0-439.module_f29+4843+69c15bdd"
    ]
}