{
    "info": {
        "Name": "varnish",
        "Version": "6.3.2",
        "Release": "3.fc30",
        "Architecture": "x86_64",
        "Size": "1.3 M",
        "Source": "varnish-6.3.2-3.fc30.src.rpm",
        "Repository": "updates",
        "Summary": "High-performance HTTP accelerator",
        "URL": "https://www.varnish-cache.org/",
        "License": "BSD",
        "Description": "This is Varnish Cache, a high-performance HTTP accelerator."
    },
    "list": [
        "varnish.i686                         6.1.1-4.fc30                        fedora",
        "varnish.x86_64                       6.1.1-4.fc30                        fedora",
        "varnish.i686                         6.3.2-3.fc30                        updates",
        "varnish.x86_64                       6.3.2-3.fc30                        updates"
    ],
    "kojiPackages": [
        "varnish-6.0.6-1.module_f30+8031+0d0c75d5",
        "varnish-6.0.6-1.module_f30+7889+dcd60497",
        "varnish-6.3.2-3.fc30",
        "varnish-6.3.1-1.fc30",
        "varnish-6.3.0-1.fc30",
        "varnish-6.1.1-4.fc30",
        "varnish-6.1.1-3.fc30",
        "varnish-6.1.1-2.fc30",
        "varnish-6.1.0-3.fc30",
        "varnish-6.1.0-2.fc30",
        "varnish-6.0.1-3.fc30",
        "varnish-6.0.1-2.fc30",
        "varnish-6.0.1-1.fc30"
    ]
}