{
    "info": {
        "Name": "bind",
        "Epoch": "32",
        "Version": "9.11.22",
        "Release": "1.fc31",
        "Architecture": "x86_64",
        "Size": "2.0 M",
        "Source": "bind-9.11.22-1.fc31.src.rpm",
        "Repository": "updates",
        "Summary": "The Berkeley Internet Name Domain (BIND) DNS (Domain Name System) server",
        "URL": "https://www.isc.org/downloads/bind/",
        "License": "MPLv2.0",
        "Description": "BIND (Berkeley Internet Name Domain) is an implementation of the DNS"
    },
    "list": [
        "bind.x86_64                      32:9.11.11-1.fc31                       fedora",
        "bind.x86_64                      32:9.11.22-1.fc31                       updates"
    ]
}