{
    "info": {
        "Name": "varnish",
        "Version": "7.0.3",
        "Release": "2.fc36",
        "Architecture": "x86_64",
        "Size": "1.1 M",
        "Source": "varnish-7.0.3-2.fc36.src.rpm",
        "Repository": "updates",
        "Summary": "High-performance HTTP accelerator",
        "URL": "https://www.varnish-cache.org/",
        "License": "BSD",
        "Description": "This is Varnish Cache, a high-performance HTTP accelerator."
    },
    "list": [
        "varnish.i686                         7.0.2-1.fc36                        fedora",
        "varnish.x86_64                       7.0.2-1.fc36                        fedora",
        "varnish.i686                         7.0.3-2.fc36                        updates",
        "varnish.x86_64                       7.0.3-2.fc36                        updates"
    ]
}