{
    "info": {
        "Name": "nodejs",
        "Epoch": "1",
        "Version": "20.18.2",
        "Release": "1.module+el8.10.0+22767+a3309b10",
        "Architecture": "x86_64",
        "Size": "14 M",
        "Source": "nodejs-20.18.2-1.module+el8.10.0+22767+a3309b10.src.rpm",
        "Repository": "rhel-8-for-x86_64-appstream-rpms",
        "Summary": "JavaScript runtime",
        "URL": "http://nodejs.org/",
        "License": "MIT and ASL 2.0 and ISC and BSD",
        "Description": "Node.js is a platform built on Chrome's JavaScript runtime"
    },
    "list": [
        "nodejs.x86_64                          1:20.5.1-1.module+el8.9.0+19645+fd8381c1                             rhel-8-for-x86_64-appstream-rpms",
        "nodejs.x86_64                          1:20.8.1-1.module+el8.9.0+20473+c4e3d824                             rhel-8-for-x86_64-appstream-rpms",
        "nodejs.x86_64                          1:20.9.0-1.module+el8.9.0+20634+bcbf506f                             rhel-8-for-x86_64-appstream-rpms",
        "nodejs.x86_64                          1:20.11.0-1.module+el8.9.0+21189+3307ab20                            rhel-8-for-x86_64-appstream-rpms",
        "nodejs.x86_64                          1:20.11.1-1.module+el8.9.0+21380+12032667                            rhel-8-for-x86_64-appstream-rpms",
        "nodejs.x86_64                          1:20.12.2-2.module+el8.9.0+21743+0b3f1be2                            rhel-8-for-x86_64-appstream-rpms",
        "nodejs.x86_64                          1:20.16.0-1.module+el8.10.0+22203+a88c8310                           rhel-8-for-x86_64-appstream-rpms",
        "nodejs.x86_64                          1:20.18.2-1.module+el8.10.0+22767+a3309b10                           rhel-8-for-x86_64-appstream-rpms"
    ]
}