{
    "info": {
        "Name": "nginx",
        "Epoch": "1",
        "Version": "1.20.1",
        "Release": "1.module_el8.8.0+3624+abf02be4.1.alma.1",
        "Architecture": "x86_64",
        "Size": "592 k",
        "Source": "nginx-1.20.1-1.module_el8.8.0+3624+abf02be4.1.alma.1.src.rpm",
        "Repository": "repo.almalinux.org_vault_8.8_AppStream_x86_64_os_",
        "Summary": "A high performance web server and reverse proxy server",
        "URL": "http://nginx.org/",
        "License": "BSD",
        "Description": "Nginx is a web server and a reverse proxy server for HTTP, SMTP, POP3 and"
    },
    "list": [
        "nginx.x86_64     1:1.20.0-2.module_el8.5.0+2575+1b759a19.alma          repo.almalinux.org_vault_8.5_AppStream_x86_64_os_",
        "nginx.x86_64     1:1.20.1-1.module_el8.5.0+2611+ab304644.alma          repo.almalinux.org_vault_8.5_AppStream_x86_64_os_",
        "nginx.x86_64     1:1.20.1-1.module_el8.6.0+2782+a022aca3.alma          repo.almalinux.org_vault_8.6_AppStream_x86_64_os_",
        "nginx.x86_64     1:1.20.1-1.module_el8.6.0+2782+a022aca3.alma          repo.almalinux.org_vault_8.7_AppStream_x86_64_os_",
        "nginx.x86_64     1:1.20.1-1.module_el8.6.0+2782+a022aca3.alma          repo.almalinux.org_vault_8.8_AppStream_x86_64_os_",
        "nginx.x86_64     1:1.20.1-1.module_el8.8.0+3624+abf02be4.1.alma.1      appstream",
        "nginx.x86_64     1:1.20.1-1.module_el8.8.0+3624+abf02be4.1.alma.1      repo.almalinux.org_vault_8.8_AppStream_x86_64_os_"
    ]
}