{
    "info": {
        "Name": "ruby",
        "Version": "3.2.4",
        "Release": "182.fc39",
        "Architecture": "x86_64",
        "Size": "40 k",
        "Source": "ruby-3.2.4-182.fc39.src.rpm",
        "Repository": "updates",
        "Summary": "An interpreter of object-oriented scripting language",
        "URL": "https://www.ruby-lang.org/",
        "License": "(Ruby OR BSD-2-Clause) AND BSD-3-Clause AND ISC AND Public Domain AND MIT and CC0 AND zlib AND Unicode-DFS-2015",
        "Description": "Ruby is the interpreted scripting language for quick and easy"
    },
    "list": [
        "ruby.i686                          3.2.2-181.fc39                        fedora",
        "ruby.x86_64                        3.2.2-181.fc39                        fedora",
        "ruby.i686                          3.2.4-182.fc39                        updates",
        "ruby.x86_64                        3.2.4-182.fc39                        updates"
    ],
    "kojiPackages": [
        "ruby-3.2.4-182.fc39",
        "ruby-3.2.2-181.fc39",
        "ruby-3.2.2-180.fc39",
        "ruby-3.2.1-179.fc39"
    ]
}